dtnclient/__init__.py
dtnclient/cli.py
dtnclient/client.py
dtnclient/eid.py
dtnclient/messages.py
dtnclient-0.2.dist-info/METADATA
dtnclient-0.2.dist-info/WHEEL
dtnclient-0.2.dist-info/entry_points.txt
dtnclient-0.2.dist-info/licenses/LICENSE
dtnclient-0.2.dist-info/RECORD
