Metadata-Version: 2.4
Name: dtnclient
Version: 0.2
Summary: Python client for dtn7-go
Project-URL: Homepage, https://github.com/dtn7/dtn-go-client
Project-URL: Bug Reports, https://github.com/dtn7/dtn-go-client/issues
Project-URL: Source, https://github.com/dtn7/dtn-go-client/dtnclient
Author-email: Markus Sommer <msommer@informatik.uni-marburg.de>, Leon Wimbes <wimbes@students.uni-marburg.de>
Maintainer-email: Markus Sommer <msommer@informatik.uni-marburg.de>
License-Expression: MIT
License-File: LICENSE
Keywords: dtn bundle_protocol
Classifier: Development Status :: 4 - Beta
Classifier: License :: OSI Approved :: MIT License
Classifier: Programming Language :: Python :: 3 :: Only
Classifier: Programming Language :: Python :: 3.12
Classifier: Programming Language :: Python :: 3.13
Classifier: Programming Language :: Python :: 3.14
Requires-Python: >=3.12
Requires-Dist: ormsgpack
